chython/__init__.py
chython/_functions.py
chython/algorithms/__init__.py
chython/algorithms/_isomorphism.cpython-311-x86_64-linux-gnu.so
chython/algorithms/_isomorphism.pyx
chython/algorithms/_rings.cpython-311-x86_64-linux-gnu.so
chython/algorithms/_rings.pyx
chython/algorithms/aromatics/__init__.py
chython/algorithms/aromatics/_rules.py
chython/algorithms/aromatics/kekule.py
chython/algorithms/aromatics/test/__init__.py
chython/algorithms/aromatics/test/test_kekule.py
chython/algorithms/aromatics/test/test_thiele.py
chython/algorithms/aromatics/thiele.py
chython/algorithms/calculate2d/__init__.py
chython/algorithms/calculate2d/clean2d.js
chython/algorithms/calculate2d/molecule.py
chython/algorithms/calculate2d/reaction.py
chython/algorithms/conformers.py
chython/algorithms/depict.py
chython/algorithms/fingerprints/__init__.py
chython/algorithms/fingerprints/linear.py
chython/algorithms/fingerprints/morgan.py
chython/algorithms/fingerprints/test/__init__.py
chython/algorithms/fingerprints/test/test_linear.py
chython/algorithms/fingerprints/test/test_morgan.py
chython/algorithms/isomorphism.py
chython/algorithms/mapping/__init__.py
chython/algorithms/mapping/_groups.py
chython/algorithms/mapping/_reactions.py
chython/algorithms/mapping/attention.py
chython/algorithms/mapping/fixmapper.py
chython/algorithms/mapping/groups.py
chython/algorithms/mcs.py
chython/algorithms/morgan.py
chython/algorithms/rings.py
chython/algorithms/smiles.py
chython/algorithms/standardize/__init__.py
chython/algorithms/standardize/_charged.py
chython/algorithms/standardize/_groups.py
chython/algorithms/standardize/_metal_organics.py
chython/algorithms/standardize/_reagents.py
chython/algorithms/standardize/_salts.py
chython/algorithms/standardize/_tautomers.py
chython/algorithms/standardize/molecule.py
chython/algorithms/standardize/reaction.py
chython/algorithms/standardize/resonance.py
chython/algorithms/standardize/salts.py
chython/algorithms/standardize/saturation.py
chython-2.15.1.dist-info/METADATA
chython-2.15.1.dist-info/WHEEL
chython-2.15.1.dist-info/licenses/LICENSE
chython-2.15.1.dist-info/RECORD
