Metadata-Version: 2.4
Name: chython
Version: 2.15.1
Summary: Library for processing molecules and reactions in python way
License: LGPLv3
License-File: LICENSE
Author: Ramil Nugmanov
Author-email: nougmanoff@protonmail.com
Requires-Python: >=3.8
Classifier: Environment :: Plugins
Classifier: Intended Audience :: Science/Research
Classifier: License :: OSI Approved :: GNU Lesser General Public License v3 or later (LGPLv3+)
Classifier: License :: Other/Proprietary License
Classifier: Operating System :: OS Independent
Classifier: Programming Language :: Python
Classifier: Programming Language :: Python :: 3
Classifier: Programming Language :: Python :: 3.8
Classifier: Programming Language :: Python :: 3.9
Classifier: Programming Language :: Python :: 3.10
Classifier: Programming Language :: Python :: 3.11
Classifier: Programming Language :: Python :: 3.12
Classifier: Programming Language :: Python :: 3.13
Classifier: Programming Language :: Python :: 3.14
Classifier: Programming Language :: Python :: 3 :: Only
Classifier: Topic :: Scientific/Engineering
Classifier: Topic :: Scientific/Engineering :: Chemistry
Classifier: Topic :: Scientific/Engineering :: Information Analysis
Classifier: Topic :: Software Development
Classifier: Topic :: Software Development :: Libraries
Classifier: Topic :: Software Development :: Libraries :: Python Modules
Provides-Extra: extra-clean2d
Provides-Extra: extra-clean3d
Provides-Extra: mapping
Provides-Extra: png
Provides-Extra: racer-default
Provides-Extra: racer-deprecated
Provides-Extra: rdkit
Requires-Dist: cachedmethods (>=0.1.4)
Requires-Dist: cdpkit (>=1.2.3) ; extra == "extra-clean3d"
Requires-Dist: chytorch-rxnmap (>=1.4) ; extra == "mapping"
Requires-Dist: jpype1 (>=1.6.0) ; extra == "extra-clean2d"
Requires-Dist: lazy-object-proxy (>=1.6)
Requires-Dist: lxml (>=4.1)
Requires-Dist: mini-racer (>=0.12.4) ; extra == "racer-default"
Requires-Dist: numpy (>=1.21.0)
Requires-Dist: openbabel-wheel (>=3.1.1.22) ; extra == "extra-clean2d"
Requires-Dist: py-mini-racer (>=0.6.0) ; extra == "racer-deprecated"
Requires-Dist: pyppeteer (>=2.0.0) ; extra == "png"
Requires-Dist: rdkit (>=2023.9) ; extra == "rdkit"
Project-URL: Documentation, https://chython.readthedocs.io
Project-URL: Homepage, https://github.com/chython/chython
